logarithm/__init__.py
logarithm/logarithm.py
logarithm-0.0.2.dist-info/LICENSE
logarithm-0.0.2.dist-info/METADATA
logarithm-0.0.2.dist-info/WHEEL
logarithm-0.0.2.dist-info/top_level.txt
logarithm-0.0.2.dist-info/RECORD
