Metadata-Version: 2.1
Name: logarithm
Version: 0.0.2
Summary: Function to find the logarithm
Home-page: https://github.com/AlexRomantsov/logarithm
Author: Alex Romantsov
Author-email: dadakil486@gmai.com
License: UNKNOWN
Platform: UNKNOWN
Classifier: Programming Language :: Python :: 3
Classifier: License :: OSI Approved :: MIT License
Classifier: Operating System :: OS Independent
